[
  { "code": "1306", "name": "NEXT FUNDS TOPIX連動型上場投信", "nickname": null, "issuer": "野村アセットマネジメント", "index_name": "TOPIX", "category": "国内株式", "themes": ["インデックス", "大型株"], "is_leveraged": false, "is_inverse": false, "expense_ratio": 0.0968, "aum": 22000000000000 },
  { "code": "1321", "name": "NEXT FUNDS 日経225連動型上場投信", "nickname": null, "issuer": "野村アセットマネジメント", "index_name": "日経平均株価", "category": "国内株式", "themes": ["インデックス", "大型株"], "is_leveraged": false, "is_inverse": false, "expense_ratio": 0.176, "aum": 8500000000000 },
  { "code": "1570", "name": "NEXT FUNDS 日経平均レバレッジ・インデックス連動型上場投信", "nickname": "日経レバ", "issuer": "野村アセットマネジメント", "index_name": "日経平均レバレッジ・インデックス", "category": "国内株式", "themes": ["レバレッジ"], "is_leveraged": true, "is_inverse": false, "expense_ratio": 0.88, "aum": 700000000000 },
  { "code": "1357", "name": "NEXT FUNDS 日経平均ダブルインバース指数連動型上場投信", "nickname": "日経ダブルインバース", "issuer": "野村アセットマネジメント", "index_name": "日経平均ダブルインバース指数", "category": "国内株式", "themes": ["インバース"], "is_leveraged": false, "is_inverse": true, "expense_ratio": 0.88, "aum": 350000000000 },
  { "code": "1655", "name": "iシェアーズ S&P500 米国株 ETF", "nickname": null, "issuer": "ブラックロック・ジャパン", "index_name": "S&P500", "category": "外国株式", "themes": ["インデックス", "米国株"], "is_leveraged": false, "is_inverse": false, "expense_ratio": 0.077, "aum": 400000000000 },
  { "code": "2558", "name": "MAXIS米国株式(S&P500)上場投信", "nickname": null, "issuer": "三菱UFJ国際投信", "index_name": "S&P500", "category": "外国株式", "themes": ["インデックス", "米国株"], "is_leveraged": false, "is_inverse": false, "expense_ratio": 0.077, "aum": 900000000000 },
  { "code": "1343", "name": "NEXT FUNDS 東証REIT指数連動型上場投信", "nickname": null, "issuer": "野村アセットマネジメント", "index_name": "東証REIT指数", "category": "REIT", "themes": ["インデックス", "REIT"], "is_leveraged": false, "is_inverse": false, "expense_ratio": 0.1705, "aum": 500000000000 },
  { "code": "1540", "name": "純金上場信託(現物国内保管型)", "nickname": "金の果実", "issuer": "三菱UFJ信託銀行", "index_name": "金価格", "category": "コモディティ", "themes": ["コモディティ", "金"], "is_leveraged": false, "is_inverse": false, "expense_ratio": 0.44, "aum": 150000000000 }
]
